mpec_extract/__init__.py
mpec_extract/extract.py
mpec_extract/extract_enums.py
mpec_extract/extract_helper.py
mpec_extract/test_function.py
mpec_extract-1.0.0.dist-info/licenses/LICENSE
mpec_extract-1.0.0.dist-info/METADATA
mpec_extract-1.0.0.dist-info/WHEEL
mpec_extract-1.0.0.dist-info/top_level.txt
mpec_extract-1.0.0.dist-info/RECORD
