Metadata-Version: 2.4
Name: mpec_extract
Version: 1.0.0
Summary: A library to extract from CEPAC and STOP output files
Author-email: Livia Qoshe <lqoshe@mgh.harvard.edu>
License-Expression: MIT
Project-URL: Homepage, https://gitlab-scm.partners.org/mpec-dev/extract_backend
Classifier: Programming Language :: Python :: 3
Classifier: Operating System :: OS Independent
Requires-Python: >=3.9
License-File: LICENSE
Dynamic: license-file
